ntfs_sds_parser-0.1.0.dist-info/METADATA
ntfs_sds_parser-0.1.0.dist-info/WHEEL
ntfs_sds_parser/__init__.py
ntfs_sds_parser/ntfs_sds_parser.cpython-38-x86_64-linux-gnu.so
ntfs_sds_parser-0.1.0.dist-info/RECORD
