Metadata-Version: 2.1
Name: ntfs_sds_parser
Version: 0.1.0
Classifier: Intended Audience :: Developers
Classifier: License :: OSI Approved :: MIT License
Classifier: Operating System :: MacOS :: MacOS X
Classifier: Operating System :: POSIX
Classifier: Programming Language :: Rust
Classifier: Programming Language :: Python
Classifier: Programming Language :: Python :: Implementation :: CPython
Classifier: Programming Language :: Python :: Implementation :: PyPy
Summary: Python bindings for https://github.com/AbdulRhmanAlfaifi/SDSParser-rs
Keywords: DFIR,forensics,$sds,ntfs
Home-Page: https://github.com/AbdulRhmanAlfaifi/SDSParser-py
Author: AbdulRhman Alfaifi
Author-email: aalfaifi@u0041.co
License: MIT or Apache-2.0
Requires-Python: >=3.7
Project-URL: Source Code, https://github.com/AbdulRhmanAlfaifi/SDSParser-py
